[
  {
    "title": "Jagonews24 | বস্তুনিষ্ঠ সংবাদের অনলাইন ঠিকানা",
    "imgUrl": "https://cdn.jagonews24.com/media/common/logo.png",
    "pdfUrl": "https://www.jagonews24.com/"
  },
  {
    "title": "Banglanews24",
    "imgUrl": "https://www.banglanews24.com/public/desktop/img/bn24_logo_3.jpg",
    "pdfUrl": "https://www.banglanews24.com/"
  },
  {
    "title": "bdnews24.com",
    "imgUrl": "https://bangla.bdnews24.com/frontend/assets/images/common/logo.png",
    "pdfUrl": "https://bangla.bdnews24.com/"
  },
  {
    "title": "Amadershomoy",
    "imgUrl": "https://admin.dainikamadershomoy.com/images/medium/default.png",
    "pdfUrl": "https://dainikamadershomoy.com/"
  },
  {
    "title": "BD24Live.com | Bangla Online News Portal",
    "imgUrl": "https://www.bd24live.com/bangla/public/logo-bd24live.png",
    "pdfUrl": "https://www.bd24live.com/bangla/"
  }
]
